azure_iothub_provisioningserviceclient-1.2.0.dist-info/METADATA
azure_iothub_provisioningserviceclient-1.2.0.dist-info/RECORD
azure_iothub_provisioningserviceclient-1.2.0.dist-info/WHEEL
azure_iothub_provisioningserviceclient-1.2.0.dist-info/top_level.txt
provisioningserviceclient/__init__.py
provisioningserviceclient/client.py
provisioningserviceclient/models.py
provisioningserviceclient/protocol/__init__.py
provisioningserviceclient/protocol/provisioning_service_client.py
provisioningserviceclient/protocol/version.py
provisioningserviceclient/protocol/models/__init__.py
provisioningserviceclient/protocol/models/attestation_mechanism.py
provisioningserviceclient/protocol/models/attestation_mechanism_py3.py
provisioningserviceclient/protocol/models/bulk_enrollment_operation.py
provisioningserviceclient/protocol/models/bulk_enrollment_operation_error.py
provisioningserviceclient/protocol/models/bulk_enrollment_operation_error_py3.py
provisioningserviceclient/protocol/models/bulk_enrollment_operation_py3.py
provisioningserviceclient/protocol/models/bulk_enrollment_operation_result.py
provisioningserviceclient/protocol/models/bulk_enrollment_operation_result_py3.py
provisioningserviceclient/protocol/models/custom_allocation_definition.py
provisioningserviceclient/protocol/models/custom_allocation_definition_py3.py
provisioningserviceclient/protocol/models/device_capabilities.py
provisioningserviceclient/protocol/models/device_capabilities_py3.py
provisioningserviceclient/protocol/models/device_registration_state.py
provisioningserviceclient/protocol/models/device_registration_state_py3.py
provisioningserviceclient/protocol/models/enrollment_group.py
provisioningserviceclient/protocol/models/enrollment_group_py3.py
provisioningserviceclient/protocol/models/individual_enrollment.py
provisioningserviceclient/protocol/models/individual_enrollment_py3.py
provisioningserviceclient/protocol/models/initial_twin.py
provisioningserviceclient/protocol/models/initial_twin_properties.py
provisioningserviceclient/protocol/models/initial_twin_properties_py3.py
provisioningserviceclient/protocol/models/initial_twin_py3.py
provisioningserviceclient/protocol/models/metadata.py
