Metadata-Version: 2.1
Name: azure-iothub-provisioningserviceclient
Version: 1.2.0
Summary: IoT Hub Provisioning Service Client Library
Home-page: https://github.com/Azure/azure-iot-sdk-python/tree/master/provisioning_service_client
Author: aziotclb
Author-email: aziotclb@microsoft.com
License: Apache Software License
Platform: UNKNOWN
Classifier: Development Status :: 5 - Production/Stable
Classifier: Intended Audience :: Developers
Classifier: Topic :: Software Development :: Build Tools
Classifier: License :: OSI Approved :: Apache Software License
Classifier: Programming Language :: Python :: 2
Classifier: Programming Language :: Python :: 2.7
Classifier: Programming Language :: Python :: 3
Classifier: Programming Language :: Python :: 3.4
Classifier: Programming Language :: Python :: 3.5
Classifier: Programming Language :: Python :: 3.6
Classifier: Programming Language :: Python :: 3.7
Requires-Dist: msrest
